ordinal_pytorch/__init__.py
ordinal_pytorch/forward.py
ordinal_pytorch/injection.py
ordinal_pytorch/ordinalify.py
ordinal_pytorch-0.1.0.dist-info/LICENSE
ordinal_pytorch-0.1.0.dist-info/METADATA
ordinal_pytorch-0.1.0.dist-info/WHEEL
ordinal_pytorch-0.1.0.dist-info/RECORD
