Metadata-Version: 2.1
Name: ordinal-pytorch
Version: 0.1.0
Summary: Library for adding ordinal classification functionality to PyTorch models.
Home-page: https://github.com/Timom1996/ordinal-pytorch
License: GPL-3.0-only
Author: Timo Michel
Author-email: timo.michel1996@outlook.de
Requires-Python: >=3.10,<4.0
Classifier: License :: OSI Approved :: GNU General Public License v3 (GPLv3)
Classifier: Programming Language :: Python :: 3
Classifier: Programming Language :: Python :: 3.10
Classifier: Programming Language :: Python :: 3.11
Requires-Dist: condor-pytorch (>=1.1.0,<2.0.0)
Requires-Dist: coral-pytorch (>=1.4.0,<2.0.0)
Requires-Dist: torch (>=2.0.1,<3.0.0)
Project-URL: Repository, https://github.com/Timom1996/ordinal-pytorch
